{
  "11161": {
    "name": "Bethel Teaching and Referral Hospital",
    "county": "Addis Ababa",
    "sub_county": "Kolfe Keranyo"
  },
  "13015": {
    "name": "Betezeta General Hospital",
    "county": "Addis Ababa",
    "sub_county": "Kirkos"
  },
  "24979": {
    "name": "Bella Military Referral Hospital",
    "county": "Addis Ababa",
    "sub_county": "Yeka"
  },
  "13080": {
    "name": "Addis Ketema Health Centre",
    "county": "Addis Ababa",
    "sub_county": "Addis Ketema"
  },
  "13122": {
    "name": "Kadisco General Hospital",
    "county": "Addis Ababa",
    "sub_county": "Addis Ketema"
  },
  "14080": {
    "name": "Adama Hospital Medical College",
    "county": "Oromia",
    "sub_county": "Aba Geda"
  },
  "11141": {
    "name": "Defense Specialized Referral Hospital",
    "county": "Oromia",
    "sub_county": "Bishoftu"
  },
  "13738": {
    "name": "Sister Aklesa Hospital",
    "county": "Oromia",
    "sub_county": "Adama"
  },
  "13156": {
    "name": "Digalu-Tijo Primary Hospital",
    "county": "Oromia",
    "sub_county": "Digalu-Tijo"
  }
}